Lab2/Q3/q3.v
module q3(a, b, c, d, f);
	input a, b, c, d;
	output f;	
	
	wire t1, t2, t3, i4, t4;
	
	and term1(t1, a, b, c);
	and term2(t2, a, c, d);
	and term3(t3, a, b, d);
	and term4(t4, b, c, d);
	
	or final(f, t1, t2, t3, t4);	
endmodule

Lab2/Q3/q3_tb.v
`timescale 1ns/1ns
`include "q3.v"

module q3_tb();
reg a, b, c, d;
wire f;

q3 gg(a, b, c, d, f);
initial
begin
	$dumpfile("q3_tb.vcd");
	$dumpvars(0, q3_tb);
	
	a=1'b0; b=1'b0; c=1'b0; d=1'b0;
	#1; 
	a=1'b0; b=1'b0; c=1'b0; d=1'b1;
	#1;
	a=1'b0; b=1'b0; c=1'b1; d=1'b0;
	#1;
	a=1'b0; b=1'b0; c=1'b1; d=1'b1;
	#1;
	a=1'b0; b=1'b1; c=1'b0; d=1'b0;
	#1;
	a=1'b0; b=1'b1; c=1'b0; d=1'b1;
	#1;
	a=1'b0; b=1'b1; c=1'b1; d=1'b0;
	#1;
	a=1'b0; b=1'b1; c=1'b1; d=1'b1;
	#1;
	a=1'b1; b=1'b0; c=1'b0; d=1'b0;
	#1;
	a=1'b1; b=1'b0; c=1'b0; d=1'b1;
	#1;
	a=1'b1; b=1'b0; c=1'b1; d=1'b0;
	#1;
	a=1'b1; b=1'b0; c=1'b1; d=1'b1;
	#1;
	a=1'b1; b=1'b1; c=1'b0; d=1'b0;
	#1;
	a=1'b1; b=1'b1; c=1'b0; d=1'b1;
	#1;
	a=1'b1; b=1'b1; c=1'b1; d=1'b0;
	#1;
	a=1'b1; b=1'b1; c=1'b1; d=1'b1;
	#1;
	
	$display("test complete");
end

endmodule

Lab2/Q3/q3_tb.vcd
$date
	Sat Aug  8 11:10:23 2026
$end
$version
	Icarus Verilog
$end
$timescale
	1ns
$end
$scope module q3_tb $end
$var wire 1 ! f $end
$var reg 1 " a $end
$var reg 1 # b $end
$var reg 1 $ c $end
$var reg 1 % d $end
$scope module gg $end
$var wire 1 " a $end
$var wire 1 # b $end
$var wire 1 $ c $end
$var wire 1 % d $end
$var wire 1 ! f $end
$var wire 1 & t1 $end
$var wire 1 ' t2 $end
$var wire 1 ( t3 $end
$var wire 1 ) t4 $end
$upscope $end
$upscope $end
$enddefinitions $end
#0
$dumpvars
0)
0(
0'
0&
0%
0$
0#
0"
0!
$end
#1
1%
#2
0%
1$
#3
1%
#4
0%
0$
1#
#5
1%
#6
0%
1$
#7
1!
1)
1%
#8
0!
0)
0%
0$
0#
1"
#9
1%
#10
0%
1$
#11
1!
1'
1%
#12
0!
0'
0%
0$
1#
#13
1!
1(
1%
#14
0(
1&
0%
1$
#15
1'
1(
1)
1%
