Lab1/L2-i/l2i.v
module l2i(a, b, c, d, f, g);
    input a, b, c, d;
    output f, g;
    
    wire nand_out;
    
    nand n1(nand_out, a, b);
    xor x1(f, d, nand_out, c);
    nor nor1(g, b, c, d);
    
endmodule

Lab1/L2-i/l2i_tb.v
`timescale 1ns/1ns
`include "l2i.v"

module l2i_tb();
reg a, b, c, d;
wire f, g;

l2i gg(a, b, c, d, f, g);
initial
begin
	$dumpfile("l2i_tb.vcd");
	$dumpvars(0, l2i_tb);
	
	a=1'b0; b=1'b0; c=1'b0; d=1'b0;
	#1; 
	a=1'b0; b=1'b0; c=1'b0; d=1'b1;
	#1;
	a=1'b0; b=1'b0; c=1'b1; d=1'b0;
	#1;
	a=1'b0; b=1'b0; c=1'b1; d=1'b1;
	#1;
	a=1'b0; b=1'b1; c=1'b0; d=1'b0;
	#1;
	a=1'b0; b=1'b1; c=1'b0; d=1'b1;
	#1;
	a=1'b0; b=1'b1; c=1'b1; d=1'b0;
	#1;
	a=1'b0; b=1'b1; c=1'b1; d=1'b1;
	#1;
	a=1'b1; b=1'b0; c=1'b0; d=1'b0;
	#1;
	a=1'b1; b=1'b0; c=1'b0; d=1'b1;
	#1;
	a=1'b1; b=1'b0; c=1'b1; d=1'b0;
	#1;
	a=1'b1; b=1'b0; c=1'b1; d=1'b1;
	#1;
	a=1'b1; b=1'b1; c=1'b0; d=1'b0;
	#1;
	a=1'b1; b=1'b1; c=1'b0; d=1'b1;
	#1;
	a=1'b1; b=1'b1; c=1'b1; d=1'b0;
	#1;
	a=1'b1; b=1'b1; c=1'b1; d=1'b1;
	#1;
	
	$display("test complete");
end

endmodule

Lab1/L2-i/l2i_tb.vcd
$date
	Sat Aug  1 10:23:53 2026
$end
$version
	Icarus Verilog
$end
$timescale
	1ns
$end
$scope module l2i_tb $end
$var wire 1 ! g $end
$var wire 1 " f $end
$var reg 1 # a $end
$var reg 1 $ b $end
$var reg 1 % c $end
$var reg 1 & d $end
$scope module gg $end
$var wire 1 # a $end
$var wire 1 $ b $end
$var wire 1 % c $end
$var wire 1 & d $end
$var wire 1 " f $end
$var wire 1 ! g $end
$var wire 1 ' nand_out $end
$upscope $end
$upscope $end
$enddefinitions $end
#0
$dumpvars
1'
0&
0%
0$
0#
1"
1!
$end
#1
0"
0!
1&
#2
0&
1%
#3
1"
1&
#4
0&
0%
1$
#5
0"
1&
#6
0&
1%
#7
1"
1&
#8
1!
0&
0%
0$
1#
#9
0"
0!
1&
#10
0&
1%
#11
1"
1&
#12
0"
0'
0&
0%
1$
#13
1"
1&
#14
0&
1%
#15
0"
1&
