Lab1/L2-ii/l2ii.v
module l2ii(a, b, c, d, f, g);
    input a, b, c, d;
    output f, g;
    
    wire w1;
    assign w1 = !(a & b);
    assign f = d ^ w1 ^ c;
    assign g = !(b | c | d);
endmodule

Lab1/L2-ii/l2ii_tb.v
`timescale 1ns/1ns
`include "l2ii.v"

module l2ii_tb();
reg a, b, c, d;
wire f, g;

l2ii gg(a, b, c, d, f, g);
initial
begin
	$dumpfile("l2ii_tb.vcd");
	$dumpvars(0, l2ii_tb);
	
	a=1'b0; b=1'b0; c=1'b0; d=1'b0;
	#1; 
	a=1'b0; b=1'b0; c=1'b0; d=1'b1;
	#1;
	a=1'b0; b=1'b0; c=1'b1; d=1'b0;
	#1;
	a=1'b0; b=1'b0; c=1'b1; d=1'b1;
	#1;
	a=1'b0; b=1'b1; c=1'b0; d=1'b0;
	#1;
	a=1'b0; b=1'b1; c=1'b0; d=1'b1;
	#1;
	a=1'b0; b=1'b1; c=1'b1; d=1'b0;
	#1;
	a=1'b0; b=1'b1; c=1'b1; d=1'b1;
	#1;
	a=1'b1; b=1'b0; c=1'b0; d=1'b0;
	#1;
	a=1'b1; b=1'b0; c=1'b0; d=1'b1;
	#1;
	a=1'b1; b=1'b0; c=1'b1; d=1'b0;
	#1;
	a=1'b1; b=1'b0; c=1'b1; d=1'b1;
	#1;
	a=1'b1; b=1'b1; c=1'b0; d=1'b0;
	#1;
	a=1'b1; b=1'b1; c=1'b0; d=1'b1;
	#1;
	a=1'b1; b=1'b1; c=1'b1; d=1'b0;
	#1;
	a=1'b1; b=1'b1; c=1'b1; d=1'b1;
	#1;
	
	$display("test complete");
end

endmodule

Lab1/L2-ii/l2ii_tb.vcd
$date
	Sat Aug  1 10:30:57 2026
$end
$version
	Icarus Verilog
$end
$timescale
	1ns
$end
$scope module l2ii_tb $end
$var wire 1 ! g $end
$var wire 1 " f $end
$var reg 1 # a $end
$var reg 1 $ b $end
$var reg 1 % c $end
$var reg 1 & d $end
$scope module gg $end
$var wire 1 # a $end
$var wire 1 $ b $end
$var wire 1 % c $end
$var wire 1 & d $end
$var wire 1 " f $end
$var wire 1 ' w1 $end
$var wire 1 ! g $end
$upscope $end
$upscope $end
$enddefinitions $end
#0
$dumpvars
1'
0&
0%
0$
0#
1"
1!
$end
#1
0"
0!
1&
#2
0"
0&
1%
#3
1"
1&
#4
1"
0&
0%
1$
#5
0"
1&
#6
0"
0&
1%
#7
1"
1&
#8
1!
1"
0&
0%
0$
1#
#9
0"
0!
1&
#10
0"
0&
1%
#11
1"
1&
#12
0"
0'
0&
0%
1$
#13
1"
1&
#14
1"
0&
1%
#15
0"
1&
