Lab1/L1-ii/l1ii.v
module l1ii(a, b, c, d, f);
	input a, b, c, d;
	output f;
	assign f = (((a & b) | c) | d) & (!((a & b) | c) & d);
endmodule

Lab1/L1-ii/l1ii_tb.v
`timescale 1ns/1ns
`include "l1ii.v"

module l1ii_tb();
reg a, b, c, d;
wire f;

l1ii gg(a, b, c, d, f);
initial
begin
	$dumpfile("l1ii_tb.vcd");
	$dumpvars(0, l1ii_tb);
	
	a=1'b0; b=1'b0; c=1'b0; d=1'b0;
	#1; 
	a=1'b0; b=1'b0; c=1'b0; d=1'b1;
	#1;
	a=1'b0; b=1'b0; c=1'b1; d=1'b0;
	#1;
	a=1'b0; b=1'b0; c=1'b1; d=1'b1;
	#1;
	a=1'b0; b=1'b1; c=1'b0; d=1'b0;
	#1;
	a=1'b0; b=1'b1; c=1'b0; d=1'b1;
	#1;
	a=1'b0; b=1'b1; c=1'b1; d=1'b0;
	#1;
	a=1'b0; b=1'b1; c=1'b1; d=1'b1;
	#1;
	a=1'b1; b=1'b0; c=1'b0; d=1'b0;
	#1;
	a=1'b1; b=1'b0; c=1'b0; d=1'b1;
	#1;
	a=1'b1; b=1'b0; c=1'b1; d=1'b0;
	#1;
	a=1'b1; b=1'b0; c=1'b1; d=1'b1;
	#1;
	a=1'b1; b=1'b1; c=1'b0; d=1'b0;
	#1;
	a=1'b1; b=1'b1; c=1'b0; d=1'b1;
	#1;
	a=1'b1; b=1'b1; c=1'b1; d=1'b0;
	#1;
	a=1'b1; b=1'b1; c=1'b1; d=1'b1;
	#1;
	
	$display("test complete");
end

endmodule

Lab1/L1-ii/l1ii_tb.vcd
$date
	Sat Aug  1 10:17:47 2026
$end
$version
	Icarus Verilog
$end
$timescale
	1ns
$end
$scope module l1ii_tb $end
$var wire 1 ! f $end
$var reg 1 " a $end
$var reg 1 # b $end
$var reg 1 $ c $end
$var reg 1 % d $end
$scope module gg $end
$var wire 1 " a $end
$var wire 1 # b $end
$var wire 1 $ c $end
$var wire 1 % d $end
$var wire 1 ! f $end
$upscope $end
$upscope $end
$enddefinitions $end
#0
$dumpvars
0%
0$
0#
0"
0!
$end
#1
1!
1%
#2
0!
0%
1$
#3
1%
#4
0%
0$
1#
#5
1!
1%
#6
0!
0%
1$
#7
1%
#8
0%
0$
0#
1"
#9
1!
1%
#10
0!
0%
1$
#11
1%
#12
0%
0$
1#
#13
1%
#14
0%
1$
#15
1%
