Lab2/Q1b/q1b.v
module q1b(a, b, c, d, f);
	input a, b, c, d;
	output f;	
	
	wire not_a, not_b, not_c, not_d, t1, t2, t3;
	not nota(not_a, a);
	not notb(not_b, b);
	not notc(not_c, c);
	not notd(not_d, d);
	
	and term1(t1, not_b, d);
	and term2(t2, not_b, c);
	and term3(t3, b, not_c, not_d);
	
	or final(f, t1, t2, t3);	
endmodule

Lab2/Q1b/q1b_tb.v
`timescale 1ns/1ns
`include "q1b.v"

module q1b_tb();
reg a, b, c, d;
wire f;

q1b gg(a, b, c, d, f);
initial
begin
	$dumpfile("q1b_tb.vcd");
	$dumpvars(0, q1b_tb);
	
	a=1'b0; b=1'b0; c=1'b0; d=1'b0;
	#1; 
	a=1'b0; b=1'b0; c=1'b0; d=1'b1;
	#1;
	a=1'b0; b=1'b0; c=1'b1; d=1'b0;
	#1;
	a=1'b0; b=1'b0; c=1'b1; d=1'b1;
	#1;
	a=1'b0; b=1'b1; c=1'b0; d=1'b0;
	#1;
	a=1'b0; b=1'b1; c=1'b0; d=1'b1;
	#1;
	a=1'b0; b=1'b1; c=1'b1; d=1'b0;
	#1;
	a=1'b0; b=1'b1; c=1'b1; d=1'b1;
	#1;
	a=1'b1; b=1'b0; c=1'b0; d=1'b0;
	#1;
	a=1'b1; b=1'b0; c=1'b0; d=1'b1;
	#1;
	a=1'b1; b=1'b0; c=1'b1; d=1'b0;
	#1;
	a=1'b1; b=1'b0; c=1'b1; d=1'b1;
	#1;
	a=1'b1; b=1'b1; c=1'b0; d=1'b0;
	#1;
	a=1'b1; b=1'b1; c=1'b0; d=1'b1;
	#1;
	a=1'b1; b=1'b1; c=1'b1; d=1'b0;
	#1;
	a=1'b1; b=1'b1; c=1'b1; d=1'b1;
	#1;
	
	$display("test complete");
end

endmodule

Lab2/Q1b/q1b_tb.vcd
$date
	Sat Aug  8 10:32:37 2026
$end
$version
	Icarus Verilog
$end
$timescale
	1ns
$end
$scope module q1b_tb $end
$var wire 1 ! f $end
$var reg 1 " a $end
$var reg 1 # b $end
$var reg 1 $ c $end
$var reg 1 % d $end
$scope module gg $end
$var wire 1 " a $end
$var wire 1 # b $end
$var wire 1 $ c $end
$var wire 1 % d $end
$var wire 1 ! f $end
$var wire 1 & not_a $end
$var wire 1 ' not_b $end
$var wire 1 ( not_c $end
$var wire 1 ) not_d $end
$var wire 1 * t1 $end
$var wire 1 + t2 $end
$var wire 1 , t3 $end
$upscope $end
$upscope $end
$enddefinitions $end
#0
$dumpvars
0,
0+
0*
1)
1(
1'
1&
0%
0$
0#
0"
0!
$end
#1
1!
0)
1*
1%
#2
1)
0*
0(
1+
0%
1$
#3
0)
1*
1%
#4
1,
1!
1)
0*
1(
0+
0'
0%
0$
1#
#5
0!
0,
0)
1%
#6
1)
0(
0%
1$
#7
0)
1%
#8
1)
1(
1'
0&
0%
0$
0#
1"
#9
1!
0)
1*
1%
#10
1)
0*
0(
1+
0%
1$
#11
0)
1*
1%
#12
1,
1!
1)
0*
1(
0+
0'
0%
0$
1#
#13
0!
0,
0)
1%
#14
1)
0(
0%
1$
#15
0)
1%
