Lab0/example1/example1.v
module example1(x1,x2,x3,f);
	input x1,x2,x3;
	output f;
	assign f = (x1 & x2) | (~x2 & x3);
endmodule

Lab0/example1/example1_tb.v
`timescale 1ns/1ns
`include "example1.v"

module example1_tb();
reg x1, x2, x3;
wire f;

example1 ex1(x1, x2, x3, f);
initial
begin
	$dumpfile("example1_tb.vcd");
	$dumpvars(0, example1_tb);

	x1=1'b0; x2=1'b0; x3=1'b0;
	#1;

	x1=1'b0; x2=1'b0; x3=1'b1;
	#1;

	x1=1'b0; x2=1'b1; x3=1'b0;
	#1;

	x1=1'b0; x2=1'b1; x3=1'b1;
	#1;

	x1=1'b1; x2=1'b0; x3=1'b0;
	#1;

	x1=1'b1; x2=1'b0; x3=1'b1;
	#1;

	x1=1'b1; x2=1'b1; x3=1'b0;
	#1;

	x1=1'b1; x2=1'b1; x3=1'b1;
	#1;
	
	$display("test complete");

end
endmodule

Lab0/example1/example1_tb.vcd
$date
	Sat Jul 25 09:35:12 2026
$end
$version
	Icarus Verilog
$end
$timescale
	1ns
$end
$scope module example1_tb $end
$var wire 1 ! f $end
$var reg 1 " x1 $end
$var reg 1 # x2 $end
$var reg 1 $ x3 $end
$scope module ex1 $end
$var wire 1 ! f $end
$var wire 1 " x1 $end
$var wire 1 # x2 $end
$var wire 1 $ x3 $end
$upscope $end
$upscope $end
$enddefinitions $end
#0
$dumpvars
0$
0#
0"
0!
$end
#1
1!
1$
#2
0!
0$
1#
#3
1$
#4
0$
0#
1"
#5
1!
1$
#6
0$
1#
#7
1$
