Lab1/L1-i/l1i.v
module l1i(a, b, c, d, f);
	input a, b, c, d;
	output f;	
	
	wire a1, o1, n1, a2, o2;
	and and1(a1, a, b);
	or or1(o1, a1, c);
	not not1(n1, o1);
	and and2(a2, n1, d);
	or or2(o2, o1, d);
	and and3(f, a2, o2);
	
endmodule

Lab1/L1-i/l1i_tb.v
`timescale 1ns/1ns
`include "l1i.v"

module l1i_tb();
reg a, b, c, d;
wire f;

l1i gg(a, b, c, d, f);
initial
begin
	$dumpfile("l1i_tb.vcd");
	$dumpvars(0, l1i_tb);
	
	a=1'b0; b=1'b0; c=1'b0; d=1'b0;
	#1; 
	a=1'b0; b=1'b0; c=1'b0; d=1'b1;
	#1;
	a=1'b0; b=1'b0; c=1'b1; d=1'b0;
	#1;
	a=1'b0; b=1'b0; c=1'b1; d=1'b1;
	#1;
	a=1'b0; b=1'b1; c=1'b0; d=1'b0;
	#1;
	a=1'b0; b=1'b1; c=1'b0; d=1'b1;
	#1;
	a=1'b0; b=1'b1; c=1'b1; d=1'b0;
	#1;
	a=1'b0; b=1'b1; c=1'b1; d=1'b1;
	#1;
	a=1'b1; b=1'b0; c=1'b0; d=1'b0;
	#1;
	a=1'b1; b=1'b0; c=1'b0; d=1'b1;
	#1;
	a=1'b1; b=1'b0; c=1'b1; d=1'b0;
	#1;
	a=1'b1; b=1'b0; c=1'b1; d=1'b1;
	#1;
	a=1'b1; b=1'b1; c=1'b0; d=1'b0;
	#1;
	a=1'b1; b=1'b1; c=1'b0; d=1'b1;
	#1;
	a=1'b1; b=1'b1; c=1'b1; d=1'b0;
	#1;
	a=1'b1; b=1'b1; c=1'b1; d=1'b1;
	#1;
	
	$display("test complete");
end

endmodule

Lab1/L1-i/l1i_tb.vcd
$date
	Sat Aug  1 10:14:14 2026
$end
$version
	Icarus Verilog
$end
$timescale
	1ns
$end
$scope module l1i_tb $end
$var wire 1 ! f $end
$var reg 1 " a $end
$var reg 1 # b $end
$var reg 1 $ c $end
$var reg 1 % d $end
$scope module gg $end
$var wire 1 " a $end
$var wire 1 & a1 $end
$var wire 1 ' a2 $end
$var wire 1 # b $end
$var wire 1 $ c $end
$var wire 1 % d $end
$var wire 1 ! f $end
$var wire 1 ( n1 $end
$var wire 1 ) o1 $end
$var wire 1 * o2 $end
$upscope $end
$upscope $end
$enddefinitions $end
#0
$dumpvars
0*
0)
1(
0'
0&
0%
0$
0#
0"
0!
$end
#1
1!
1'
1*
1%
#2
0!
0(
0'
1)
0%
1$
#3
1%
#4
1(
0*
0)
0%
0$
1#
#5
1!
1'
1*
1%
#6
0!
0(
0'
1)
0%
1$
#7
1%
#8
1(
0*
0)
0%
0$
0#
1"
#9
1!
1'
1*
1%
#10
0!
0(
0'
1)
0%
1$
#11
1%
#12
1&
0%
0$
1#
#13
1%
#14
0%
1$
#15
1%
